csc_cyb600_lab1_TimeApp-1.0.0.data/scripts/web_sync.py
cyb600_lab1/__init__.py
cyb600_lab1/web_app.py
csc_cyb600_lab1_TimeApp-1.0.0.dist-info/LICENSE
csc_cyb600_lab1_TimeApp-1.0.0.dist-info/METADATA
csc_cyb600_lab1_TimeApp-1.0.0.dist-info/WHEEL
csc_cyb600_lab1_TimeApp-1.0.0.dist-info/top_level.txt
csc_cyb600_lab1_TimeApp-1.0.0.dist-info/RECORD
